LICENSE
MANIFEST.in
README.md
dependencies.txt
setup.py
stackq/__init__.py
stackq/config.py
stackq/io.py
stackq/stack.py
stackq/stackq.py
stackq/utils.py
stackq.egg-info/PKG-INFO
stackq.egg-info/SOURCES.txt
stackq.egg-info/dependency_links.txt
stackq.egg-info/entry_points.txt
stackq.egg-info/requires.txt
stackq.egg-info/top_level.txt