Metadata-Version: 1.1
Name: stackq
Version: 0.0.0-alpha.1.2
Summary: Get answers through your command line 
Home-page: https://github.com/stackq
Author: Forfuture LLC
Author-email: we@forfuture.co.ke
License: MIT
Download-URL: https://github.com/forfuture-dev/stackq/zipball/master
Keywords: cli,terminal,stackoverflow,stackexchange,answers
Platform: UNKNOWN
Classifier: Development Status :: 2 - Pre-Alpha
Classifier: Environment :: Console
Classifier: Intended Audience :: End Users/Desktop
Classifier: License :: OSI Approved
Classifier: License :: OSI Approved :: MIT License
Classifier: Natural Language :: English
Classifier: Operating System :: OS Independent
Classifier: Programming Language :: Python
Classifier: Programming Language :: Python :: 2
Classifier: Programming Language :: Python :: 2.6
Classifier: Programming Language :: Python :: 2.7
